odoo9_addon_website_snippet_big_button-9.0.1.0.0-py2.7-nspkg.pth
odoo_addons/website_snippet_big_button/__openerp__.py
odoo_addons/website_snippet_big_button/__init__.py
odoo_addons/website_snippet_big_button/README.rst
odoo_addons/website_snippet_big_button/templates/snippets.xml
odoo_addons/website_snippet_big_button/templates/assets.xml
odoo_addons/website_snippet_big_button/i18n/es.po
odoo_addons/website_snippet_big_button/i18n/sl.po
odoo_addons/website_snippet_big_button/static/description/icon.svg
odoo_addons/website_snippet_big_button/static/description/icon.png
odoo_addons/website_snippet_big_button/static/src/js/website_snippet_big_button.js
odoo_addons/website_snippet_big_button/static/src/css/website_snippet_big_button.sass
odoo9_addon_website_snippet_big_button-9.0.1.0.0.dist-info/top_level.txt
odoo9_addon_website_snippet_big_button-9.0.1.0.0.dist-info/WHEEL
odoo9_addon_website_snippet_big_button-9.0.1.0.0.dist-info/RECORD
odoo9_addon_website_snippet_big_button-9.0.1.0.0.dist-info/metadata.json
odoo9_addon_website_snippet_big_button-9.0.1.0.0.dist-info/DESCRIPTION.rst
odoo9_addon_website_snippet_big_button-9.0.1.0.0.dist-info/METADATA
odoo9_addon_website_snippet_big_button-9.0.1.0.0.dist-info/namespace_packages.txt
