Metadata-Version: 2.0
Name: odoo9-addon-website-snippet-big-button
Version: 9.0.1.0.0
Summary: A snippet that adds two big buttons
Home-page: https://www.tecnativa.com/
Author: Grupo ESOC Ingeniería de Servicios, S.L.U., Tecnativa, Odoo Community Association (OCA)
Author-email: support@odoo-community.org
License: LGPL-3
Platform: UNKNOWN
Requires-Dist: odoo (<9.1a,>=9.0a)
Classifier: Programming Language :: Python :: 2.7
Classifier: Framework :: Odoo
Classifier: License :: OSI Approved :: GNU Lesser General Public License v3 (LGPLv3)
